epub2speech/__init__.py
epub2speech/chapter_tts.py
epub2speech/cli.py
epub2speech/convertor.py
epub2speech/epub_picker.py
epub2speech/extractor.py
epub2speech/m4b_generator.py
epub2speech/tts/__init__.py
epub2speech/tts/azure_provider.py
epub2speech/tts/doubao_provider.py
epub2speech/tts/protocol.py
epub2speech-0.0.5.dist-info/LICENSE
epub2speech-0.0.5.dist-info/METADATA
epub2speech-0.0.5.dist-info/WHEEL
epub2speech-0.0.5.dist-info/entry_points.txt
epub2speech-0.0.5.dist-info/RECORD
