Metadata-Version: 2.3
Name: epub2speech
Version: 0.0.5
Summary: Convert EPUB e-books into high-quality audiobooks using multiple Text-to-Speech providers (Azure, Doubao)
License: MIT
Keywords: epub,audiobook,text-to-speech,tts,azure,doubao,m4b,ebook
Author: TaoZeyu
Author-email: i@taozeyu.com
Maintainer: TaoZeyu
Maintainer-email: i@taozeyu.com
Requires-Python: >=3.11,<3.14
Classifier: Development Status :: 4 - Beta
Classifier: Intended Audience :: End Users/Desktop
Classifier: License :: OSI Approved :: MIT License
Classifier: Operating System :: OS Independent
Classifier: Programming Language :: Python :: 3
Classifier: Programming Language :: Python :: 3.11
Classifier: Programming Language :: Python :: 3.12
Classifier: Programming Language :: Python :: 3.13
Classifier: Topic :: Multimedia :: Sound/Audio :: Conversion
Classifier: Topic :: Text Processing :: Markup
Classifier: Topic :: Utilities
Provides-Extra: dev
Requires-Dist: azure-cognitiveservices-speech (>=1.46.0,<2.0.0)
Requires-Dist: ebooklib (>=0.19,<0.20)
Requires-Dist: numpy (>=1.24.0,<3.0.0)
Requires-Dist: pillow (>=11.3.0,<12.0.0)
Requires-Dist: pylint (>=3.0.0) ; extra == "dev"
Requires-Dist: pytest (>=7.0.0) ; extra == "dev"
Requires-Dist: pytest-cov (>=4.0.0) ; extra == "dev"
Requires-Dist: python-dotenv (>=1.0.0,<2.0.0) ; extra == "dev"
Requires-Dist: requests (>=2.32.4,<3.0.0)
Requires-Dist: resource-segmentation (>=0.0.7,<0.1.0)
Requires-Dist: scipy (>=1.10.0,<2.0.0)
Requires-Dist: soundfile (>=0.13.1,<0.14.0)
Requires-Dist: spacy (>=3.8.7,<4.0.0)
Project-URL: Bug Tracker, https://github.com/oomol-lab/epub2speech/issues
Project-URL: Documentation, https://github.com/oomol-lab/epub2speech/blob/main/README.md
Project-URL: Homepage, https://github.com/oomol-lab/epub2speech
Project-URL: Repository, https://github.com/oomol-lab/epub2speech
